Workbook

Sheet Estimate Summary
A1: PAINTING & WALLCOVERING ESTIMATE
A2: Boot Barn Store #1660 — Columbia, SC
A3: 10050 Two Notch Road, Space/Suite #1, Columbia, SC 29223
A4: Bid Date: March 19, 2026 | Prepared by: Carolina Commercial Finishes
A5: Budget Painting and Wallcovering LLC | 3308 Chancellor Lane, Monroe, NC 28110 | (980) 348-1827
A6: Date Prepared: March 19, 2026 — SOW-VALIDATED ESTIMATE
A8: SCOPE CATEGORY | B8: LABOR HRS | C8: LABOR $ | D8: MATERIALS $ | E8: DIRECT COST | F8: % OF TOTAL
A9: 1. Interior Walls — Sales Area (P-3, WC-3, WD-5) | B9: ='Interior Walls'!I7 -> 77.589667 | C9: ='Interior Walls'!J7 -> 2172.5107 | D9: ='Interior Walls'!K7 -> 1379.676 | E9: =C9+D9 -> 3552.1867 | F9: =IF(E15=0,0,E9/E15) -> 0.13185192
A10: 2. Interior Walls — Back of House (P-3, 8 rooms) | B10: ='Interior Walls'!I19 -> 143.44318 | C10: ='Interior Walls'!J19 -> 4016.4092 | D10: ='Interior Walls'!K19 -> 3408.6708 | E10: =C10+D10 -> 7425.08 | F10: =IF(E15=0,0,E10/E15) -> 0.27560799
A11: 3. Ceilings — Open Deck P-1 Dryfall | B11: =Ceilings!G4 -> 247.99426 | C11: =Ceilings!H4 -> 6943.8393 | D11: =Ceilings!I4 -> 2967.9953 | E11: =C11+D11 -> 9911.8346 | F11: =IF(E15=0,0,E11/E15) -> 0.36791264
A12: 4. Doors & Frames (21 units) | B12: ='Doors & Frames'!E6 -> 30.5 | C12: ='Doors & Frames'!F6 -> 854 | D12: ='Doors & Frames'!H6 -> 239.22 | E12: =C12+D12 -> 1093.22 | F12: =IF(E15=0,0,E12/E15) -> 0.04057871
A13: 5. Exterior Painting (P-6 CMU) | B13: =Exterior!F4 -> 4.479 | C13: =Exterior!G4 -> 125.412 | D13: =Exterior!H4 -> 128.9952 | E13: =C13+D13 -> 254.4072 | F13: =IF(E15=0,0,E13/E15) -> 0.009443219
A14: 6. Prep, Misc & Equipment | B14: ='Prep & Misc'!F12 -> 68 | C14: ='Prep & Misc'!G12 -> 1904 | D14: ='Prep & Misc'!H12 -> 2800 | E14: =C14+D14 -> 4704 | F14: =IF(E15=0,0,E14/E15) -> 0.17460552
A15: DIRECT COST TOTALS | B15: =SUM(B9:B14) -> 572.00611 | C15: =SUM(C9:C14) -> 16016.171 | D15: =SUM(D9:D14) -> 10924.557 | E15: =SUM(E9:E14) -> 26940.729 | F15: 1
A17: Direct Cost | E17: =E15 -> 26940.729
A18: Overhead (12%) | E18: =E17*0.12 -> 3232.8874
A19: Markup (18%) | E19: =(E17+E18)*0.18 -> 5431.2509
A20: BID PRICE (PAINTING & WALLCOVERING) | E20: =E17+E18+E19 -> 35604.867
A22: KEY METRICS
A23: Total Paintable SF (SOW-adjusted): | B23: ='Interior Walls'!E20+Ceilings!C3*0.95+Exterior!C3 -> 33835.471
A24: Takeoff Total SF (before SOW): | B24: ='Interior Walls'!C20+Ceilings!C3+Exterior!C3 -> 35179.86
A25: Blended Rate ($/SF): | B25: =IF(B23=0,0,E20/B23) -> 1.0522941
A26: Total Labor Hours: | B26: =B15 -> 572.00611
A27: Estimated Duration (2-man crew): | B27: =ROUNDUP(B26/(2*8),0)&" working days" -> 36 working days
A28: Estimated Duration (3-man crew): | B28: =ROUNDUP(B26/(3*8),0)&" working days" -> 24 working days
A29: Labor Rate (burdened): | B29: $28.00/hr
A31: EXCLUSIONS
A32: • Electrostatic painting of any equipment
A33: • Floor markings or striping
A34: • Vestibule painting (existing conditions, not in scope)
A35: • Tile areas in restrooms (below wainscot — not painted)
A36: • ACT ceiling grid painting or replacement
A37: • Pressure washing (GC scope)
A38: • Storefront glazing / window work
A39: • Signage installation
A40: • Any work above 22' (lift rental included for ceiling work up to 22')
A41: • Fixture painting or staining (by fixture vendor)
A43: NOTES
... A53: • SOW adjustments validated against architectural drawings (sheets A30, A30.1)

Sheet Interior Walls
A1: INTERIOR WALLS — SOW-VALIDATED BREAKDOWN
A2: SECTION A: SALES AREA (by finish system)
A3: # | B3: Room / Area | C3: Takeoff SF | D3: SOW % | E3: Paint SF | F3: Method | G3: Coats | H3: Paint System | I3: Labor Hrs | J3: Labor $ | K3: Material $ | L3: Total $ | M3: Night
A4: 1 | B4: Sales Area P-3 Walls | C4: 4718.2 | D4: 1 | E4: =C4*D4 -> 4718.2 | F4: Spray+BR | G4: P+2 | H4: SW ProMar 200 Zero VOC Eggshell | I4: =E4/250*2 -> 37.7456 | J4: =I4*28 -> 1056.8768 | K4: =E4/400*22 + E4/350*28*2 -> 1014.413 | L4: =J4+K4 -> 2071.2898
A5: 2 | B5: Sales Area WC-3 Wallcovering | C5: 1811.61 | D5: 1 | E5: =C5*D5 -> 1811.61 | F5: Hand Hang | G5: 1 App | H5: Brewster Commercial Vinyl (tenant-supplied) | I5: =E5/50*1 -> 36.2322 | J5: =I5*28 -> 1014.5016 | K5: =E5*0.15 -> 271.7415 | L5: =J5+K5 -> 1286.2431
A6: 3 | B6: Sales Area WD-5 Wood Stain | C6: 270.89 | D6: 1 | E6: =C6*D6 -> 270.89 | F6: Brush | G6: S+2P | H6: SW WoodClassics Stain + Poly | I6: =E6/75*1 -> 3.6118667 | J6: =I6*28 -> 101.13227 | K6: =E6/300*35 + E6/350*40*2 -> 93.521548 | L6: =J6+K6 -> 194.65381
B7: SECTION A SUBTOTAL | C7: =SUM(C4:C6) -> 6800.7 | E7: =SUM(E4:E6) -> 6800.7 | I7: =SUM(I4:I6) -> 77.589667 | J7: =SUM(J4:J6) -> 2172.5107 | K7: =SUM(K4:K6) -> 1379.676 | L7: =SUM(L4:L6) -> 3552.1867
A9: SECTION B: BACK OF HOUSE (all P-3 system)
A10: # | B10: Room / Area | C10: Takeoff SF | D10: SOW % | E10: Paint SF | F10: Method | G10: Coats | H10: Paint System | I10: Labor Hrs | J10: Labor $ | K10: Material $ | L10: Total $ | M10: Night
A11: 4 | B11: Stockroom | C11: 9070.95 | D11: 1 | E11: =C11*D11 -> 9070.95 | F11: Spray | G11: P+2 | H11: SW ProMar 200 Zero VOC Eggshell | I11: =E11/300*2 -> 60.473 | J11: =I11*28 -> 1693.244 | K11: =E11/400*22 + E11/350*28*2 -> 1950.2542 | L11: =J11+K11 -> 3643.4983
A12: 5 | B12: Elec Room | C12: 1117.07 | D12: 1 | E12: =C12*D12 -> 1117.07 | F12: B&R | G12: P+2 | H12: SW ProMar 200 Zero VOC Eggshell | I12: =E12/175*2 -> 12.766514 | J12: =I12*28 -> 357.4624 | K12: =E12/400*22 + E12/350*28*2 -> 240.17005 | L12: =J12+K12 -> 597.63245
A13: 6 | B13: Utility Closet | C13: 701.97 | D13: 1 | E13: =C13*D13 -> 701.97 | F13: B&R | G13: P+2 | H13: SW ProMar 200 Zero VOC Eggshell | I13: =E13/175*2 -> 8.0225143 | J13: =I13*28 -> 224.6304 | K13: =E13/400*22 + E13/350*28*2 -> 150.92355 | L13: =J13+K13 -> 375.55395
A14: 7 | B14: Manager's Office | C14: 611.11 | D14: 1 | E14: =C14*D14 -> 611.11 | F14: B&R | G14: P+2 | H14: SW ProMar 200 Zero VOC Eggshell | I14: =E14/175*2 -> 6.9841143 | J14: =I14*28 -> 195.5552 | K14: =E14/400*22 + E14/350*28*2 -> 131.38865 | L14: =J14+K14 -> 326.94385
A15: 8 | B15: Restrooms | C15: 1548.19 | D15: 0.75 | E15: =C15*D15 -> 1161.1425 | F15: B&R | G15: P+2 | H15: SW ProMar 200 Zero VOC Eggshell | I15: =E15/150*2 -> 15.4819 | J15: =I15*28 -> 433.4932 | K15: =E15/400*22 + E15/350*28*2 -> 249.64564 | L15: =J15+K15 -> 683.13884
A16: 9 | B16: Hallway to Restrooms | C16: 833.56 | D16: 0.9 | E16: =C16*D16 -> 750.204 | F16: B&R | G16: P+2 | H16: SW ProMar 200 Zero VOC Eggshell | I16: =E16/175*2 -> 8.57376 | J16: =I16*28 -> 240.06528 | K16: =E16/400*22 + E16/350*28*2 -> 161.29386 | L16: =J16+K16 -> 401.35914
A17: 10 | B17: Fitting Rooms | C17: 1997.89 | D17: 0.85 | E17: =C17*D17 -> 1698.2065 | F17: B&R | G17: P+2 | H17: SW ProMar 200 Zero VOC Eggshell | I17: =E17/150*2 -> 22.642753 | J17: =I17*28 -> 633.99709 | K17: =E17/400*22 + E17/350*28*2 -> 365.1144 | L17: =J17+K17 -> 999.11149
A18: 11 | B18: Closet | C18: 743.63 | D18: 1 | E18: =C18*D18 -> 743.63 | F18: B&R | G18: P+2 | H18: SW ProMar 200 Zero VOC Eggshell | I18: =E18/175*2 -> 8.4986286 | J18: =I18*28 -> 237.9616 | K18: =E18/400*22 + E18/350*28*2 -> 159.88045 | L18: =J18+K18 -> 397.84205
B19: SECTION B SUBTOTAL | C19: =SUM(C11:C18) -> 16624.37 | E19: =SUM(E11:E18) -> 15854.283 | I19: =SUM(I11:I18) -> 143.44318 | J19: =SUM(J11:J18) -> 4016.4092 | K19: =SUM(K11:K18) -> 3408.6708 | L19: =SUM(L11:L18) -> 7425.08
B20: INTERIOR WALLS — GRAND TOTAL | C20: =C7+C19 -> 23425.07 | E20: =E7+E19 -> 22654.983 | I20: =I7+I19 -> 221.03285 | J20: =J7+J19 -> 6188.9198 | K20: =K7+K19 -> 4788.3469 | L20: =L7+L19 -> 10977.267
A22: SOW ADJUSTMENT NOTES
A23: • Stockroom: 100% — Full height new GWB walls, all paintable
A24: • Elec Room / Utility / Manager's Office / Closet: 100% — All new construction GWB
A25: • Restrooms: 75% — Deducted tile wainscot areas below 4' (tile not painted)
A26: • Hallway: 90% — Minor deductions for door openings along corridor
A27: • Fitting Rooms: 85% — Partial walls with fixture mounts/hooks reducing paintable area
A28: • Sales Area P-3: 100% — Togal takeoff already isolates paint walls from WC-3/WD-5 areas
A29: • WC-3 Wallcovering: 100% — Full area as identified in Togal; material supplied by tenant
A30: • WD-5 Wood Stain: 100% — Wood trim/millwork as identified in drawings

Sheet Ceilings
A1: CEILINGS — BY TYPE & AREA
A2: Area / Room | B2: Ceiling Type | C2: Total SF | D2: Prod Rate (SF/hr) | E2: Coats | F2: Paint System | G2: Labor Hrs | H2: Labor $ | I2: Material $ | J2: Total $
A3: Sales Area Open Deck Ceiling | B3: Exposed Structure/Deck (Dryfall) | C3: 11486.05 | D3: 110 | E3: P+2 | F3: SW ProIndustrial WB Acrylic Dryfall (P-1) | G3: =C3*0.95/D3*2.5 -> 247.99426 | H3: =G3*28 -> 6943.8393 | I3: =C3*0.95/250*20 + C3*0.95/250*24*2 -> 2967.9953 | J3: =H3+I3 -> 9911.8346
A4: CEILING TOTALS | C4: =SUM(C3) -> 11486.05 | G4: =SUM(G3) -> 247.99426 | H4: =SUM(H3) -> 6943.8393 | I4: =SUM(I3) -> 2967.9953 | J4: =SUM(J3) -> 9911.8346
A6: NOTES
A7: • P-1 ceiling is exposed structure (steel joists, beams, metal deck, ductwork) — NOT flat GWB
A8: • Production rate 110 SF/hr accounts for irregular surfaces, spray from lift
A9: • 95% SOW applied — minor deductions for HVAC equipment areas
A10: • 2.5 coat factor: 1 coat primer + 2 coats dryfall finish
A11: • Scissor lift required — rental cost on Prep & Misc sheet
A12: • BOH ceilings (Stockroom, Elec, Utility, Closet) are open-to-deck and NOT painted per BOH standard
A13: • Manager's Office and Restroom ceilings are existing ACT — NOT painted

Sheet Doors & Frames
A1: DOORS & FRAMES — ITEMIZED
A2: Item # | B2: Description | C2: Qty | D2: Hrs/Unit | E2: Total Hrs | F2: Labor $ | G2: Mat $/Unit | H2: Total Mat $ | I2: Total $
A3: 1 | B3: Single Swing HM Doors + Frames (per door schedule) | C3: 16 | D3: 1.5 | E3: =C3*D3 -> 24 | F3: =E3*28 -> 672 | G3: 11.67 | H3: =C3*G3 -> 186.72 | I3: =F3+H3 -> 858.72
A4: 2 | B4: Double Swing Door + Frame | C4: 1 | D4: 2.5 | E4: =C4*D4 -> 2.5 | F4: =E4*28 -> 70 | G4: 17.5 | H4: =C4*G4 -> 17.5 | I4: =F4+H4 -> 87.5
A5: 3 | B5: Sliding Doors (spray) | C5: 4 | D5: 1 | E5: =C5*D5 -> 4 | F5: =E5*28 -> 112 | G5: 8.75 | H5: =C5*G5 -> 35 | I5: =F5+H5 -> 147
B6: DOOR TOTALS | C6: =SUM(C3:C5) -> 21 | E6: =SUM(E3:E5) -> 30.5 | F6: =SUM(F3:F5) -> 854 | H6: =SUM(H3:H5) -> 239.22 | I6: =SUM(I3:I5) -> 1093.22
A8: NOTES
A9: • All HM doors per door schedule — SW ProIndustrial DTM Acrylic Semi-Gloss, 2 coats
A10: • Sliding doors sprayed — lower labor rate per unit
A11: • Frame painting included in per-unit hours
A12: • Hardware masked — not removed

Sheet Exterior
A1: EXTERIOR PAINTING
A2: Item # | B2: Description | C2: Qty / SF | D2: Unit | E2: Prod Rate | F2: Labor Hrs | G2: Labor $ | H2: Material $ | I2: Total $
A3: 1 | B3: Exterior CMU Walls (P-6) | C3: 268.74 | D3: SF | E3: 150 | F3: =C3/E3*2.5 -> 4.479 | G3: =F3*28 -> 125.412 | H3: =C3/100*28 + C3/300*30*2 -> 128.9952 | I3: =G3+H3 -> 254.4072
B4: EXTERIOR TOTALS | C4: =SUM(C3) -> 268.74 | F4: =SUM(F3) -> 4.479 | G4: =SUM(G3) -> 125.412 | H4: =SUM(H3) -> 128.9952 | I4: =SUM(I3) -> 254.4072
A6: NOTES
A7: • P-6 system: SW A-100 Exterior Latex Flat — Block filler + 2 finish coats on CMU
A8: • Block filler coverage 100 SF/gal (heavy fill on new CMU)
A9: • Spray application with backroll

Sheet Prep & Misc
A1: PREP, MISC & EQUIPMENT
A2: Item # | B2: Description | C2: Qty | D2: Unit | E2: Rate/Hr | F2: Labor Hrs | G2: Labor $ | H2: Material $ | I2: Total $
A3: 1 | B3: Surface Prep — Skim/Patch New GWB | C3: 10 | D3: HR | E3: 28 | F3: 10 | G3: =F3*28 -> 280 | H3: 0 | I3: =G3+H3 -> 280
A4: 2 | B4: Caulking — Joints & Transitions | C4: 6 | D4: HR | E4: 28 | F4: 6 | G4: =F4*28 -> 168 | H4: 0 | I4: =G4+H4 -> 168
A5: 3 | B5: Floor/Fixture Masking & Protection | C5: 16 | D5: HR | E5: 28 | F5: 16 | G5: =F5*28 -> 448 | H5: 0 | I5: =G5+H5 -> 448
A6: 4 | B6: Sprayer Rental (8 days × $150/day) | C6: 1 | D6: LS | G6: 0 | H6: 1200 | I6: =G6+H6 -> 1200
A7: 5 | B7: Scissor Lift Rental (5 days × $250/day) | C7: 1 | D7: LS | G7: 0 | H7: 1250 | I7: =G7+H7 -> 1250
A8: 6 | B8: Mob/Demob (2-man crew, Monroe NC → Columbia SC) | C8: 12 | D8: HR | E8: 28 | F8: 12 | G8: =F8*28 -> 336 | H8: 0 | I8: =G8+H8 -> 336
A9: 7 | B9: Daily Setup/Cleanup (1 hr/day × 12 days) | C9: 12 | D9: HR | E9: 28 | F9: 12 | G9: =F9*28 -> 336 | H9: 0 | I9: =G9+H9 -> 336
A10: 8 | B10: Touch-up / Punch List | C10: 12 | D10: HR | E10: 28 | F10: 12 | G10: =F10*28 -> 336 | H10: 0 | I10: =G10+H10 -> 336
A11: 9 | B11: Supplies (tape, plastic, drops, rollers, tips) | C11: 1 | D11: LS | G11: 0 | H11: 350 | I11: =G11+H11 -> 350
B12: PREP & MISC TOTALS | F12: =SUM(F3:F11) -> 68 | G12: =SUM(G3:G11) -> 1904 | H12: =SUM(H3:H11) -> 2800 | I12: =SUM(I3:I11) -> 4704
