Workbook

Sheet Estimate Summary
A1: PAINTING ESTIMATE
A2: Food Lion Store #1513 Remodel — Asheboro, NC
A3: 433 State Hwy 49 S., Asheboro, NC 27203
A4: Bid Date: March 18, 2026 at 2:00 PM | Prepared by: Carolina Commercial Finishes
A5: Date Prepared: March 17, 2026 — SOW-VALIDATED ESTIMATE
A7: SCOPE CATEGORY | B7: LABOR HRS | C7: LABOR $ | D7: MATERIALS $ | E7: DIRECT COST | F7: % OF TOTAL
A8: Interior Walls (20 rooms, SOW-adjusted) | B8: ='Interior Walls'!I24 -> 313.35448 | C8: ='Interior Walls'!J24 -> 8773.9253 | D8: ='Interior Walls'!K24 -> 6351.16 | E8: =C8+D8 -> 15125.085 | F8: =E8/E13 -> 0.58038521
A9: Ceilings (Epoxy + GWB + Flat) | B9: =Ceilings!G11 -> 39.133333 | C9: =Ceilings!H11 -> 1095.7333 | D9: =Ceilings!J11 -> 1049 | E9: =C9+D9 -> 2144.7333 | F9: =E9/E13 -> 0.082298478
A10: Doors & Frames (40 units, interior) | B10: ='Doors & Frames'!H10 -> 67.033333 | C10: ='Doors & Frames'!I10 -> 1876.9333 | D10: ='Doors & Frames'!K10 -> 376 | E10: =C10+D10 -> 2252.9333 | F10: =E10/E13 -> 0.086450367
A11: Exterior Painting | B11: =Exterior!F13 -> 26.863333 | C11: =Exterior!G13 -> 752.17333 | D11: =Exterior!H13 -> 143.5 | E11: =C11+D11 -> 895.67333 | F11: =E11/E13 -> 0.034369099
A12: Prep, Misc & Equipment | B12: ='Prep & Misc'!F32 -> 156.5 | C12: ='Prep & Misc'!G32 -> 4382 | D12: ='Prep & Misc'!H32 -> 1260 | E12: =C12+D12 -> 5642 | F12: =E12/E13 -> 0.21649685
A13: DIRECT COST TOTALS | B13: =SUM(B8:B12) -> 602.88448 | C13: =SUM(C8:C12) -> 16880.765 | D13: =SUM(D8:D12) -> 9179.66 | E13: =SUM(E8:E12) -> 26060.425 | F13: 100%
A15: Direct Cost | E15: =E13 -> 26060.425
A16: Overhead (12%) | E16: =E15*0.12 -> 3127.251
A18: BID PRICE (PAINTING ONLY) | E18: =E15+E16+E17 -> 29187.676
A20: KEY METRICS
A21: Total Paintable SF (SOW-adjusted): | B21: ='Interior Walls'!E24+Ceilings!D11+'Doors & Frames'!F10+Exterior!C13 -> 27618
A22: Takeoff Total SF (before SOW adjustment): | B22: ='Interior Walls'!C24+Ceilings!D11+'Doors & Frames'!F10+Exterior!C13 -> 27618
A23: Blended Rate ($/SF): | B23: =E18/B21 -> 1.0568353
A24: Total Labor Hours: | B24: =B13 -> 602.88448
A25: Estimated Duration (2-man crew): | B25: =ROUNDUP(B24/(2*8),0)&" days" -> 38 days
A26: Estimated Duration (3-man crew): | B26: =ROUNDUP(B24/(3*8),0)&" days" -> 26 days
A27: Labor Rate (burdened): | B27: $28.00/hr
A29: EXCLUSIONS
A30: • Wallcovering / decorative wall systems (excluded per client request)
A31: • Electrostatic painting (excluded per client request)
A32: • Floor painting / traffic markings / epoxy floor systems
A33: • Vestibule aluminum/glass walls (GC scope)
A34: • Marlite installation and finishing (GC scope)
A35: • FRP installation (GC scope)
A36: • Ceramic/quarry tile surfaces
A37: • Cooler/freezer panel surfaces and interiors
A38: • Stainless steel surfaces and trim
A39: • Aluminum surfaces and storefront
A40: • Sales Floor / Backroom / Receiving exposed structure ceilings (remain as-is per RCP A1.04)
... A54: • Exterior metals: all previously painted surfaces — bollards, cart corral, alarm box, hatches, dock stairs

Sheet Interior Walls
A1: INTERIOR WALLS — SOW-VALIDATED BREAKDOWN
A3: Room # | B3: Room Name | C3: Takeoff SF | D3: SOW % | E3: Paint SF | F3: Method | G3: Coats | H3: Paint System | I3: Labor Hrs | J3: Labor $ | K3: Material $ | L3: Total $ | M3: Night
A4: 103 | B4: Sales Floor Walls | C4: 7000 | D4: 100% | E4: =C4*1 -> 7000 | F4: Spray | G4: P+2 | H4: ProBlock Primer + ProMar 200 Eg-Shel | I4: =E4*2/150 -> 93.333333 | J4: =I4*28 -> 2613.3333 | K4: =E4*2*0.12 -> 1680 | L4: =J4+K4 -> 4293.3333 | M4: Y
A5: 103C | B5: Sales Floor Columns | C5: 450 | D5: 100% | E5: =C5*1 -> 450 | F5: B&R | G5: SP+2 | H5: Spot Prime + Pre-Cat Epoxy SG K46 | I5: =E5*2/100 -> 9 | J5: =I5*28 -> 252 | K5: =E5*2*0.18 -> 162 | L5: =J5+K5 -> 414 | M5: Y
A6: 100 | B6: Front End / Vestibule Walls | C6: 800 | D6: 100% | E6: =C6*1 -> 800 | F6: Spray | G6: P+2 | H6: ProBlock Primer + ProMar 200 Eg-Shel | I6: =E6*2/150 -> 10.666667 | J6: =I6*28 -> 298.66667 | K6: =E6*2*0.12 -> 192 | L6: =J6+K6 -> 490.66667 | M6: Y
A7: 100T | B7: Ecomm Area — Pine Trim over Marlite | C7: 180 | D7: 100% | E7: =C7*1 -> 180 | F7: B&R | G7: P+2 | H7: ProMar 200 SG | I7: =E7*2/80 -> 4.5 | J7: =I7*28 -> 126 | K7: =E7*2*0.15 -> 54 | L7: =J7+K7 -> 180 | M7: Y
A8: 111 | B8: Backroom Walls | C8: 5500 | D8: 100% | E8: =C8*1 -> 5500 | F8: Spray+BR | G8: P+2 | H8: ProMar 200 Eg-Shel | I8: =E8*2/175 -> 62.857143 | J8: =I8*28 -> 1760 | K8: =E8*2*0.12 -> 1320 | L8: =J8+K8 -> 3080
A9: 101 | B9: Breakroom / Lounge | C9: 595 | D9: 100% | E9: =C9*1 -> 595 | F9: B&R | G9: SP+2 | H9: Spot Prime + ProMar 200 Eg-Shel | I9: =E9*2/150 -> 7.9333333 | J9: =I9*28 -> 222.13333 | K9: =E9*2*0.12 -> 142.8 | L9: =J9+K9 -> 364.93333
A10: 102 | B10: Restrooms | C10: 612 | D10: 100% | E10: =C10*1 -> 612 | F10: B&R | G10: SP+2 | H10: Spot Prime + ProMar 200 Eg-Shel | I10: =E10*2/150 -> 8.16 | J10: =I10*28 -> 228.48 | K10: =E10*2*0.12 -> 146.88 | L10: =J10+K10 -> 375.36
A11: 120 | B11: Managers Office | C11: 298 | D11: 100% | E11: =C11*1 -> 298 | F11: B&R | G11: SP+2 | H11: Spot Prime + ProMar 200 Eg-Shel | I11: =E11*2/150 -> 3.9733333 | J11: =I11*28 -> 111.25333 | K11: =E11*2*0.12 -> 71.52 | L11: =J11+K11 -> 182.77333
A12: 118 | B12: Receiving | C12: 1150 | D12: 100% | E12: =C12*1 -> 1150 | F12: Spray+BR | G12: SP+2 | H12: Spot Prime + Pre-Cat Epoxy Eg-Shel K45 | I12: =E12*2/125 -> 18.4 | J12: =I12*28 -> 515.2 | K12: =E12*2*0.18 -> 414 | L12: =J12+K12 -> 929.2
A13: 116 | B13: Elec. Room | C13: 251 | D13: 100% | E13: =C13*1 -> 251 | F13: B&R | G13: SP+2 | H13: Spot Prime + Pre-Cat Epoxy Eg-Shel K45 | I13: =E13*2/125 -> 4.016 | J13: =I13*28 -> 112.448 | K13: =E13*2*0.18 -> 90.36 | L13: =J13+K13 -> 202.808
A14: 115 | B14: Mech. Room | C14: 1349 | D14: 100% | E14: =C14*1 -> 1349 | F14: Spray+BR | G14: SP+2 | H14: Spot Prime + Pre-Cat Epoxy Eg-Shel K45 | I14: =E14*2/125 -> 21.584 | J14: =I14*28 -> 604.352 | K14: =E14*2*0.18 -> 485.64 | L14: =J14+K14 -> 1089.992
A15: 117 | B15: Compressor Room | C15: 418 | D15: 100% | E15: =C15*1 -> 418 | F15: B&R | G15: SP+2 | H15: Spot Prime + Pre-Cat Epoxy Eg-Shel K45 | I15: =E15*2/125 -> 6.688 | J15: =I15*28 -> 187.264 | K15: =E15*2*0.18 -> 150.48 | L15: =J15+K15 -> 337.744
A16: 114 | B16: Janitor / Storage | C16: 365 | D16: 100% | E16: =C16*1 -> 365 | F16: B&R | G16: SP+2 | H16: Spot Prime + Pre-Cat Epoxy Eg-Shel K45 | I16: =E16*2/125 -> 5.84 | J16: =I16*28 -> 163.52 | K16: =E16*2*0.18 -> 131.4 | L16: =J16+K16 -> 294.92
A17: 113 | B17: Deli/Bakery Prep | C17: 1200 | D17: 100% | E17: =C17*1 -> 1200 | F17: B&R | G17: BF+2 | H17: Kem Cati-Coat Filler + Macropoxy 646 | I17: =E17*2/100 -> 24 | J17: =I17*28 -> 672 | K17: =E17*2*0.25 -> 600 | L17: =J17+K17 -> 1272
A18: 112 | B18: Meat Prep | C18: 408 | D18: 100% | E18: =C18*1 -> 408 | F18: B&R | G18: BF+2 | H18: Kem Cati-Coat Filler + Macropoxy 646 | I18: =E18*2/100 -> 8.16 | J18: =I18*28 -> 228.48 | K18: =E18*2*0.25 -> 204 | L18: =J18+K18 -> 432.48
A19: 110 | B19: Produce Prep | C19: 266 | D19: 100% | E19: =C19*1 -> 266 | F19: B&R | G19: BF+2 | H19: Kem Cati-Coat Filler + Macropoxy 646 | I19: =E19*2/100 -> 5.32 | J19: =I19*28 -> 148.96 | K19: =E19*2*0.25 -> 133 | L19: =J19+K19 -> 281.96
A20: 109 | B20: Office | C20: 437 | D20: 100% | E20: =C20*1 -> 437 | F20: B&R | G20: SP+2 | H20: Spot Prime + ProMar 200 Eg-Shel | I20: =E20*2/150 -> 5.8266667 | J20: =I20*28 -> 163.14667 | K20: =E20*2*0.12 -> 104.88 | L20: =J20+K20 -> 268.02667
A21: 108 | B21: Cash Office | C21: 441 | D21: 100% | E21: =C21*1 -> 441 | F21: B&R | G21: SP+2 | H21: Spot Prime + ProMar 200 Eg-Shel | I21: =E21*2/150 -> 5.88 | J21: =I21*28 -> 164.64 | K21: =E21*2*0.12 -> 105.84 | L21: =J21+K21 -> 270.48
A22: 104 | B22: DSD Vestibule | C22: 451 | D22: 100% | E22: =C22*1 -> 451 | F22: B&R | G22: SP+2 | H22: Spot Prime + Pre-Cat Epoxy Eg-Shel K45 | I22: =E22*2/125 -> 7.216 | J22: =I22*28 -> 202.048 | K22: =E22*2*0.18 -> 162.36 | L22: =J22+K22 -> 364.408
A23: 105 | B23: Corridor / Back of House | D23: 0% | H23: (included in adjacent room measurements)
B24: TOTAL — Interior Walls | C24: =SUM(C4:C23) -> 22171 | E24: =SUM(E4:E23) -> 22171 | I24: =SUM(I4:I23) -> 313.35448 | J24: =SUM(J4:J23) -> 8773.9253 | K24: =SUM(K4:K23) -> 6351.16 | L24: =SUM(L4:L23) -> 15125.085
A26: SOW ADJUSTMENT NOTES
A27: • All rooms at 100% SOW — full wall painting scope per drawings and specifications
A28: • Room 105 Corridor: SF included within adjacent room measurements (backroom, receiving)
A29: • Sales floor columns counted separately from walls — different substrate and paint system
A30: • Ecomm pine trim: trim over Marlite only, not full wall — measured from walk notes
A31: • Exposed structure ceilings EXCLUDED per RCP A1.04 — remain as-is (see Ceilings tab)

Sheet Ceilings
A1: CEILINGS — BY TYPE & AREA
A3: Area / Room | B3: Ceiling Type | C3: Paint System | D3: Total SF | E3: Prod Rate | F3: Coats | G3: Labor Hrs | H3: Labor $ | I3: Mat $/SF | J3: Material $ | K3: Total $
A4: Room 113 — Deli/Bakery Prep Ceiling | B4: GWB (existing) | C4: Macropoxy 646 Epoxy P-4(D) | D4: 900 | E4: 125 | F4: 2 | G4: =D4*F4/E4 -> 14.4 | H4: =G4*28 -> 403.2 | I4: 0.25 | J4: =D4*F4*I4 -> 450 | K4: =H4+J4 -> 853.2
A5: Room 102 — Restrooms Ceiling | B5: GWB (existing) | C5: Macropoxy 646 Epoxy P-4(D) | D5: 300 | E5: 125 | F5: 2 | G5: =D5*F5/E5 -> 4.8 | H5: =G5*28 -> 134.4 | I5: 0.25 | J5: =D5*F5*I5 -> 150 | K5: =H5+J5 -> 284.4
A6: Room 100 — Vestibule Ceiling | B6: GWB (existing) | C6: ProMar 200 Flat | D6: 320 | E6: 200 | F6: 2 | G6: =D6*F6/E6 -> 3.2 | H6: =G6*28 -> 89.6 | I6: 0.1 | J6: =D6*F6*I6 -> 64 | K6: =H6+J6 -> 153.6
A7: Room 112 — Meat Prep Ceiling | B7: Plywood (existing) | C7: Macropoxy 646 Epoxy P-4(B) | D7: 350 | E7: 100 | F7: 2 | G7: =D7*F7/E7 -> 7 | H7: =G7*28 -> 196 | I7: 0.25 | J7: =D7*F7*I7 -> 175 | K7: =H7+J7 -> 371
A8: Room 110 — Produce Prep Ceiling | B8: Plywood (existing) | C8: Macropoxy 646 Epoxy P-4(B) | D8: 200 | E8: 100 | F8: 2 | G8: =D8*F8/E8 -> 4 | H8: =G8*28 -> 112 | I8: 0.25 | J8: =D8*F8*I8 -> 100 | K8: =H8+J8 -> 212
A9: Meat Office Ceiling | B9: Plywood (existing) | C9: Macropoxy 646 Epoxy P-4(B) | D9: 120 | E9: 100 | F9: 2 | G9: =D9*F9/E9 -> 2.4 | H9: =G9*28 -> 67.2 | I9: 0.25 | J9: =D9*F9*I9 -> 60 | K9: =H9+J9 -> 127.2
A10: Room 115 — Mech Room Ceiling | B10: Existing Ceiling | C10: ProMar 200 Flat | D10: 500 | E10: 150 | F10: 1 | G10: =D10*F10/E10 -> 3.3333333 | H10: =G10*28 -> 93.333333 | I10: 0.1 | J10: =D10*F10*I10 -> 50 | K10: =H10+J10 -> 143.33333
A11: TOTAL — Ceilings | D11: =SUM(D4:D10) -> 2690 | G11: =SUM(G4:G10) -> 39.133333 | H11: =SUM(H4:H10) -> 1095.7333 | J11: =SUM(J4:J10) -> 1049 | K11: =SUM(K4:K10) -> 2144.7333
A13: NOTE: Per RCP Sheet A1.04, Sales Floor / Backroom / Receiving exposed structure ceilings = NO PAINT (remain as-is). Only prep rooms and utilities with 'PREP AND PAINT' callouts included. Exposed structure rates: 100-125 SF/hr, NOT flat ceiling 300 SF/hr.

Sheet Doors & Frames
A1: DOORS & FRAMES — ITEMIZED
A3: Item # | B3: Description | C3: Paint System | D3: Qty | E3: SF/EA | F3: Total SF | G3: Prod Rate | H3: Labor Hrs | I3: Labor $ | J3: Mat $/EA | K3: Material $ | L3: Total $
A4: INTERIOR — Doors, Frames & Specialty
A5: 1 | B5: Single Swing HM Doors & Frames | C5: Pre-Cat Epoxy SG K46W150 | D5: 28 | E5: 42 | F5: =D5*E5 -> 1176 | G5: 30 | H5: =F5/G5 -> 39.2 | I5: =H5*28 -> 1097.6 | J5: 8.5 | K5: =D5*J5 -> 238 | L5: =I5+K5 -> 1335.6
A6: 2 | B6: Double Swing HM Doors & Frames | C6: Pre-Cat Epoxy SG K46W150 | D6: 5 | E6: 70 | F6: =D6*E6 -> 350 | G6: 25 | H6: =F6/G6 -> 14 | I6: =H6*28 -> 392 | J6: 14 | K6: =D6*J6 -> 70 | L6: =I6+K6 -> 462
A7: 3 | B7: Sliding Door Frames (touch-up) | C7: Pre-Cat Epoxy SG K46W150 | D7: 2 | E7: 35 | F7: =D7*E7 -> 70 | G7: 30 | H7: =F7/G7 -> 2.3333333 | I7: =H7*28 -> 65.333333 | J7: 7 | K7: =D7*J7 -> 14 | L7: =I7+K7 -> 79.333333
A8: 4 | B8: Automatic Door Packages (4 sets) | C8: DTM Acrylic SG | D8: 4 | E8: 50 | F8: =D8*E8 -> 200 | G8: 20 | H8: =F8/G8 -> 10 | I8: =H8*28 -> 280 | J8: 12 | K8: =D8*J8 -> 48 | L8: =I8+K8 -> 328
A9: 5 | B9: Office Safe (inside & sales side) | C9: ProMar 200 SG Macadamia | D9: 1 | E9: 60 | F9: =D9*E9 -> 60 | G9: 40 | H9: =F9/G9 -> 1.5 | I9: =H9*28 -> 42 | J9: 6 | K9: =D9*J9 -> 6 | L9: =I9+K9 -> 48
B10: TOTAL — Doors & Frames (Interior) | F10: =SUM(F5:F9) -> 1856 | H10: =SUM(H5:H9) -> 67.033333 | I10: =SUM(I5:I9) -> 1876.9333 | K10: =SUM(K5:K9) -> 376 | L10: =SUM(L5:L9) -> 2252.9333
A12: NOTE: Door prep per walk notes — sand smooth, remove silicone/adhesive, spot prime bare steel. Exterior doors/metals are in the Exterior tab.

Sheet Exterior
A1: EXTERIOR PAINTING
A3: Item # | B3: Description | C3: Qty / SF | D3: Unit | E3: Prod Rate | F3: Labor Hrs | G3: Labor $ | H3: Material $ | I3: Total $
A4: 1 | B4: Exterior HM Doors & Frames (6 ea) | C4: 252 | D4: SF | E4: 25 | F4: =C4/E4 -> 10.08 | G4: =F4*28 -> 282.24 | H4: 54 | I4: =G4+H4 -> 336.24
A5: 2 | B5: Bollards — traffic yellow (8 ea) | C5: 96 | D5: SF | E5: 40 | F5: =C5/E5 -> 2.4 | G5: =F5*28 -> 67.2 | H5: 24 | I5: =G5+H5 -> 91.2
A6: 3 | B6: Cart Corral — Grizzle Gray SW 7068 | C6: 200 | D6: SF | E6: 50 | F6: =C6/E6 -> 4 | G6: =F6*28 -> 112 | H6: 15 | I6: =G6+H6 -> 127
A7: 4 | B7: Alarm Box / Bell under Canopy | C7: 10 | D7: SF | E7: 40 | F7: =C7/E7 -> 0.25 | G7: =F7*28 -> 7 | H7: 2.5 | I7: =G7+H7 -> 9.5
A8: 5 | B8: Access Hatches (2 ea) | C8: 40 | D8: SF | E8: 30 | F8: =C8/E8 -> 1.3333333 | G8: =F8*28 -> 37.333333 | H8: 8 | I8: =G8+H8 -> 45.333333
A9: 6 | B9: Metal Lintels / Misc. Metals | C9: 150 | D9: SF | E9: 50 | F9: =C9/E9 -> 3 | G9: =F9*28 -> 84 | H9: 12 | I9: =G9+H9 -> 96
A10: 7 | B10: Rear Dock Stairs & Canopy Supports | C10: 120 | D10: SF | E10: 40 | F10: =C10/E10 -> 3 | G10: =F10*28 -> 84 | H10: 10 | I10: =G10+H10 -> 94
A11: 8 | B11: Light Pole Bases — prev. painted (4 ea) | C11: 32 | D11: SF | E11: 40 | F11: =C11/E11 -> 0.8 | G11: =F11*28 -> 22.4 | H11: 8 | I11: =G11+H11 -> 30.4
A12: 9 | B12: Dock Door Number Stenciling | C12: 1 | D12: LS | E12: - | F12: 2 | G12: =F12*28 -> 56 | H12: 10 | I12: =G12+H12 -> 66
B13: TOTAL — Exterior | C13: =SUM(C4:C12) -> 901 | F13: =SUM(F4:F12) -> 26.863333 | G13: =SUM(G4:G12) -> 752.17333 | H13: =SUM(H4:H12) -> 143.5 | I13: =SUM(I4:I12) -> 895.67333
A15: NOTE: All exterior metals previously painted. Paint system: DTM Acrylic SG or All Surface Enamel per walk notes. Cart corral = Grizzle Gray SW 7068. Bollards = OSHA Traffic Yellow.

Sheet Prep & Misc
A1: PREP, MISC & EQUIPMENT
A3: Item # | B3: Description | C3: Unit | D3: Qty | E3: Hrs/Unit | F3: Total Hrs | G3: Labor $ | H3: Material $ | I3: Total $
A4: SURFACE PREPARATION
A5: 1 | B5: Surface prep — scrape tape/caulk/residues all rooms | C5: LS | D5: 1 | E5: 16 | F5: =D5*E5 -> 16 | G5: =F5*28 -> 448 | H5: 80 | I5: =G5+H5 -> 528
A6: 2 | B6: Skim/patch walls — spot Level 3 (sales area) | C6: LS | D6: 1 | E6: 16 | F6: =D6*E6 -> 16 | G6: =F6*28 -> 448 | H6: 150 | I6: =G6+H6 -> 598
A7: 3 | B7: Skim/patch walls (back of house) | C7: LS | D7: 1 | E7: 8 | F7: =D7*E7 -> 8 | G7: =F7*28 -> 224 | H7: 80 | I7: =G7+H7 -> 304
A8: 4 | B8: Sand/degloss columns (120 grit) | C8: EA | D8: 12 | E8: 0.75 | F8: =D8*E8 -> 9 | G8: =F8*28 -> 252 | H8: 25 | I8: =G8+H8 -> 277
A9: 5 | B9: Prime bare/repaired areas — Extreme Bond Primer | C9: LS | D9: 1 | E9: 8 | F9: =D9*E9 -> 8 | G9: =F9*28 -> 224 | H9: 120 | I9: =G9+H9 -> 344
A10: 6 | B10: Prime bare GWB — ProBlock Oil Based (sales area) | C10: LS | D10: 1 | E10: 8 | F10: =D10*E10 -> 8 | G10: =F10*28 -> 224 | H10: 120 | I10: =G10+H10 -> 344
A11: CAULKING & SEALANT
A12: 7 | B12: Caulk fixtures — restrooms/corridors/prep areas | C12: LS | D12: 1 | E12: 8 | F12: =D12*E12 -> 8 | G12: =F12*28 -> 224 | H12: 50 | I12: =G12+H12 -> 274
A13: 8 | B13: Caulk pine trim over Marlite after GC install | C13: LS | D13: 1 | E13: 6 | F13: =D13*E13 -> 6 | G13: =F13*28 -> 168 | H13: 30 | I13: =G13+H13 -> 198
A14: 9 | B14: Caulk abandoned holes (Produce/Meat Prep) | C14: LS | D14: 1 | E14: 3 | F14: =D14*E14 -> 3 | G14: =F14*28 -> 84 | H14: 15 | I14: =G14+H14 -> 99
A15: MASKING & PROTECTION
A16: 10 | B16: Masking/protection — sales area walls (night work) | C16: LS | D16: 1 | E16: 12 | F16: =D16*E16 -> 12 | G16: =F16*28 -> 336 | H16: 100 | I16: =G16+H16 -> 436
A17: 11 | B17: Masking/protection — back of house | C17: LS | D17: 1 | E17: 8 | F17: =D17*E17 -> 8 | G17: =F17*28 -> 224 | H17: 60 | I17: =G17+H17 -> 284
A18: 12 | B18: Ceiling protection/drop cloths (prep rooms) | C18: LS | D18: 1 | E18: 3 | F18: =D18*E18 -> 3 | G18: =F18*28 -> 84 | H18: 30 | I18: =G18+H18 -> 114
A19: MEP / MISCELLANEOUS PAINTING
A20: 13 | B20: Paint PVC chase pipes on cases (match columns) | C20: LS | D20: 1 | E20: 6 | F20: =D20*E20 -> 6 | G20: =F20*28 -> 168 | H20: 30 | I20: =G20+H20 -> 198
A21: 14 | B21: Paint electrical panels (Macadamia) | C21: EA | D21: 4 | E21: 1.5 | F21: =D21*E21 -> 6 | G21: =F21*28 -> 168 | H21: 30 | I21: =G21+H21 -> 198
A22: 15 | B22: Paint angle behind safe | C22: EA | D22: 1 | E22: 0.5 | F22: =D22*E22 -> 0.5 | G22: =F22*28 -> 14 | H22: 5 | I22: =G22+H22 -> 19
A23: 16 | B23: Paint underside of shelves (walk notes) | C23: LS | D23: 1 | E23: 4 | F23: =D23*E23 -> 4 | G23: =F23*28 -> 112 | H23: 20 | I23: =G23+H23 -> 132
A24: 17 | B24: Paint deli bulkhead GWB repairs | C24: LS | D24: 1 | E24: 3 | F24: =D24*E24 -> 3 | G24: =F24*28 -> 84 | H24: 15 | I24: =G24+H24 -> 99
A25: 18 | B25: Stencil store numbers — dock doors/roll-up doors | C25: LS | D25: 1 | E25: 2 | F25: =D25*E25 -> 2 | G25: =F25*28 -> 56 | H25: 10 | I25: =G25+H25 -> 66
A26: TOUCH-UP
A27: 19 | B27: Touch-up after GC/trades work | C27: LS | D27: 1 | E27: 12 | F27: =D27*E27 -> 12 | G27: =F27*28 -> 336 | H27: 60 | I27: =G27+H27 -> 396
A28: 20 | B28: Spot prime & touch-up after fixture install | C28: LS | D28: 1 | E28: 6 | F28: =D28*E28 -> 6 | G28: =F28*28 -> 168 | H28: 30 | I28: =G28+H28 -> 198
A29: MOBILIZATION & EQUIPMENT
A30: 21 | B30: Mobilization / demobilization | C30: LS | D30: 1 | E30: 12 | F30: =D30*E30 -> 12 | G30: =F30*28 -> 336 | H30: 0 | I30: =G30+H30 -> 336
A31: 22 | B31: Baker scaffold (prep room ceilings) | C31: WK | D31: 1 | E31: 0 | F31: =D31*E31 -> 0 | G31: =F31*28 -> 0 | H31: 200 | I31: =G31+H31 -> 200
B32: TOTAL — Prep & Misc | F32: =SUM(F5:F31) -> 156.5 | G32: =SUM(G5:G31) -> 4382 | H32: =SUM(H5:H31) -> 1260 | I32: =SUM(I5:I31) -> 5642
A34: NOTE: Night work premium included in labor rates. Sales area painting, ceiling, and drywall work must be done 10pm-8am per walk notes.
